LICENSE
MANIFEST.in
README.md
setup.py
VirtuousUmami/Virtuous.py
VirtuousUmami/VirtuousUmami.py
VirtuousUmami/__init__.py
VirtuousUmami/testing_umami.py
VirtuousUmami.egg-info/PKG-INFO
VirtuousUmami.egg-info/SOURCES.txt
VirtuousUmami.egg-info/dependency_links.txt
VirtuousUmami.egg-info/top_level.txt
VirtuousUmami/src/features_list.txt
VirtuousUmami/src/length_of_features_from_training.txt
VirtuousUmami/src/maximums.txt
VirtuousUmami/src/minimums.txt
VirtuousUmami/src/models_3_5.zip
VirtuousUmami/src/training_labels.txt
VirtuousUmami/src/umami_AD.pkl
VirtuousUmami/src/umami_best_features.txt
VirtuousUmami/src/umami_statistical_features.txt
samples/test.txt
samples/test_sample.csv
samples/test_samples.csv